{"title": "INTRODUCTION TO AMERICAN URBAN HISTORY", "level": "1311", "abbreviation": "HI", "description": "Cat. I\n \nAn introduction to the history of the American city as an important phenomenon \nin itself and as a reflection of national history. The course will take an \ninterdisciplinary approach to study the political, economic, social, and\n technological patterns that have shaped the growth of urbanization. In addition\nto reading historical approaches to the study of American urban history, students\n may also examine appropriate works by sociologists, economists, political \nscientists and city planners who provide historical perspective.", "req": [], "cat1Status": true, "startYear": -1}